main.py
baiyinnamula_hello_world-0.1.0.dist-info/METADATA
baiyinnamula_hello_world-0.1.0.dist-info/WHEEL
baiyinnamula_hello_world-0.1.0.dist-info/top_level.txt
baiyinnamula_hello_world-0.1.0.dist-info/RECORD
