Metadata-Version: 2.4
Name: baiyinnamula-hello-world
Version: 0.1.0
Summary: Add your description here
Requires-Python: >=3.12
Requires-Dist: flask>=3.1.1
Requires-Dist: requests==2.31.0
